[{"testcaseMap":null,"mainMd":"public static void main(String[] args) {\nint length = 0;\n    int result = AreaCalculator.computeAreaValue(length);\n}","logicExprOfPath":" !((length * length) <= (60) && (length * length) > (4)) && !(length < 0)","logicExprOfDT":"((length % 7) >= 0 && (length % 7) < 7)","dangerousInput":false,"timeCostInMs":482.0}
,{"testcaseMap":null,"mainMd":"public static void main(String[] args) {\nint length = -31734;\n    int result = AreaCalculator.computeAreaValue(length);\n}","logicExprOfPath":" !(((0) * (0)) <= (60) && ((0) * (0)) > (4)) && (length < 0)","logicExprOfDT":"(((0) % 7) >= 0 && ((0) % 7) < 7)","dangerousInput":false,"timeCostInMs":471.0}
,{"testcaseMap":null,"mainMd":"public static void main(String[] args) {\nint length = 4;\n    int result = AreaCalculator.computeAreaValue(length);\n}","logicExprOfPath":" ((length * length) <= (60) && (length * length) > (4)) && !(length < 0)","logicExprOfDT":"((length) >= 0 && (length) < 7)","dangerousInput":false,"timeCostInMs":477.0}
,{"testcaseMap":{"length ":" 7"},"mainMd":null,"logicExprOfPath":" ((length * length) <= (60) && (length * length) > (4)) && !(length < 0)","logicExprOfDT":"((length) >= 0 && (length) < 7)","dangerousInput":true,"timeCostInMs":0.0}
]